tech_mcp_dmo/__init__.py
tech_mcp_dmo-0.1.0.dist-info/WHEEL
tech_mcp_dmo-0.1.0.dist-info/entry_points.txt
tech_mcp_dmo-0.1.0.dist-info/METADATA
tech_mcp_dmo-0.1.0.dist-info/RECORD
